khx_colory/__init__.py
khx_colory/cli.py
khx_colory/colors.py
khx_colory/core.py
khx_colory/styles.py
khx_colory/text.py
khx_colory-0.1.0.dist-info/METADATA
khx_colory-0.1.0.dist-info/WHEEL
khx_colory-0.1.0.dist-info/entry_points.txt
khx_colory-0.1.0.dist-info/licenses/LICENSE
khx_colory-0.1.0.dist-info/RECORD
