Metadata-Version: 2.4
Name: khx-colory
Version: 0.1.0
Summary: A rich terminal printing library for colorful text, lines, banners, and highlights
Project-URL: Homepage, https://github.com/KHADER/khx-colory
Project-URL: Documentation, https://github.com/KHADER/khx-colory#readme
Project-URL: Repository, https://github.com/KHADER/khx-colory
Project-URL: Issues, https://github.com/KHADER/khx-colory/issues
Author-email: KHADER <khader@example.com>
License: MIT
License-File: LICENSE
Keywords: color,console,rich,styling,terminal,text
Classifier: Development Status :: 4 - Beta
Classifier: Intended Audience :: Developers
Classifier: License :: OSI Approved :: MIT License
Classifier: Operating System :: OS Independent
Classifier: Programming Language :: Python :: 3
Classifier: Programming Language :: Python :: 3.8
Classifier: Programming Language :: Python :: 3.9
Classifier: Programming Language :: Python :: 3.10
Classifier: Programming Language :: Python :: 3.11
Classifier: Programming Language :: Python :: 3.12
Classifier: Topic :: Software Development :: Libraries :: Python Modules
Classifier: Topic :: Terminals
Classifier: Topic :: Text Processing :: Markup
Requires-Python: >=3.8
Provides-Extra: dev
Requires-Dist: black>=23.0; extra == 'dev'
Requires-Dist: isort>=5.0; extra == 'dev'
Requires-Dist: mypy>=1.0; extra == 'dev'
Requires-Dist: pytest-cov>=4.0; extra == 'dev'
Requires-Dist: pytest>=7.0; extra == 'dev'
